bdbag_gui/__init__.py
bdbag_gui/__main__.py
bdbag_gui/resources.py
bdbag_gui/images/bag.icns
bdbag_gui/images/bag.ico
bdbag_gui/images/bag.png
bdbag_gui/impl/__init__.py
bdbag_gui/impl/async_task.py
bdbag_gui/impl/bag_tasks.py
bdbag_gui/ui/__init__.py
bdbag_gui/ui/json_editor.py
bdbag_gui/ui/log_widget.py
bdbag_gui/ui/main_window.py
bdbag_gui/ui/options_window.py
bdbag_gui-1.2.1.dist-info/LICENSE
bdbag_gui-1.2.1.dist-info/METADATA
bdbag_gui-1.2.1.dist-info/WHEEL
bdbag_gui-1.2.1.dist-info/entry_points.txt
bdbag_gui-1.2.1.dist-info/top_level.txt
bdbag_gui-1.2.1.dist-info/RECORD
