Metadata-Version: 2.1
Name: bdbag_gui
Version: 1.2.1
Summary: Graphical User Interface for BDBag Utility
Home-page: https://github.com/fair-research/bdbag_gui/
Maintainer: USC Information Sciences Institute, Informatics Systems Research Division
Maintainer-email: isrd-support@isi.edu
License: GNU GPL 3.0
Classifier: Intended Audience :: Science/Research
Classifier: Intended Audience :: Developers
Classifier: License :: OSI Approved :: Apache Software License
Classifier: Operating System :: POSIX
Classifier: Operating System :: MacOS :: MacOS X
Classifier: Operating System :: Microsoft :: Windows
Classifier: Programming Language :: Python
Classifier: Programming Language :: Python :: 3.7
Classifier: Programming Language :: Python :: 3.8
Classifier: Programming Language :: Python :: 3.9
Classifier: Programming Language :: Python :: 3.10
Classifier: Programming Language :: Python :: 3.11
Requires: os
Requires: sys
Requires: logging
Requires: PyQt5
License-File: LICENSE
Requires-Dist: bdbag[boto,globus] >=1.6.0
Requires-Dist: PyQt5
